arithmatic/__init__.py
arithmatic/core.py
simple_arithmatic_ops-0.1.1.dist-info/licenses/LICENSE
simple_arithmatic_ops-0.1.1.dist-info/METADATA
simple_arithmatic_ops-0.1.1.dist-info/WHEEL
simple_arithmatic_ops-0.1.1.dist-info/top_level.txt
simple_arithmatic_ops-0.1.1.dist-info/RECORD
