Metadata-Version: 2.4
Name: simple-arithmatic-ops
Version: 0.1.1
Summary: A simple Python package for integer arithmetic operations
Home-page: 
Author: Zilberguy
Author-email: Some_random_email@gmail.com
Classifier: Programming Language :: Python :: 3
Classifier: License :: OSI Approved :: MIT License
Classifier: Operating System :: OS Independent
Requires-Python: >=3.6
License-File: LICENSE
Dynamic: author
Dynamic: author-email
Dynamic: classifier
Dynamic: description
Dynamic: description-content-type
Dynamic: license-file
Dynamic: requires-python
Dynamic: summary
